LICENSE
MANIFEST.in
README.md
pyproject.toml
pytest_nose_attrib/__init__.py
pytest_nose_attrib/plugin.py
pytest_nose_attrib.egg-info/PKG-INFO
pytest_nose_attrib.egg-info/SOURCES.txt
pytest_nose_attrib.egg-info/dependency_links.txt
pytest_nose_attrib.egg-info/entry_points.txt
pytest_nose_attrib.egg-info/requires.txt
pytest_nose_attrib.egg-info/top_level.txt