Metadata-Version: 2.1
Name: pytest-nose-attrib
Version: 0.1.1
Summary: pytest plugin to use nose @attrib marks decorators and pick tests based on attributes and partially uses nose-attrib plugin approach
Author-email: Maksim Gelbakhiani <Max.Gelbakhiani@gmail.com>
License: The MIT License (MIT)
Project-URL: Homepage, https://github.com/MaxGelbakhiani/pytest-nose-attrib
Classifier: Programming Language :: Python
Classifier: Programming Language :: Python :: 3
License-File: LICENSE
